{"H2AFZ_H1-hESC_hg19": ["CDKN1A", "RPL41", "CCDC115", "MAGED1", "NCOA4", "USMG5", "SEPW1", "COX7A2", "TRIAP1", "COMMD6", "MRPL32", "PTRHD1", "UBL5", "RUSC1", "BLOC1S2", "BSG", "GAR1", "TOMM7", "RPL36", "NUDT15", "TMEM14A", "BCAS2"], "H3K4me3_WI38_hg19": ["NMB", "NIPSNAP3A", "CCDC115", "RPS8", "SRRT", "FAM103A1", "TAF9", "NRARP", "RPS3A", "SEPW1", "H1FX-AS1", "SAT1", "SMG8", "MRPL33", "SDCBP", "UBL5", "MZT2A", "TRIM28", "CREG1", "RAB13", "PMAIP1", "NUDT15", "TP53", "IER2"], "H3K4me3_ES-E14_mm9": ["GRN", "ANAPC15", "CISD1", "SEPW1", "MRPL32", "SH3BGRL3", "SFN", "STRA13", "PHLDA2", "IER2", "POLR2K", "CACNG5", "NIPSNAP3A", "CCDC115", "NDUFA4", "YIPF3", "TMA7", "EDF1", "LSR", "SIRT7", "SLC50A1", "COMMD6", "ZWINT", "PTRHD1", "NSA2", "POLE3", "SELK", "PFN1", "GLA", "PIGF"], "H3K4me3_ES-Bruce4_mm9": ["NOP58", "NIPSNAP3A", "CCDC115", "NDUFA4", "PRKCSH", "GTF3C6", "RBM18", "GLRX2", "ZWINT", "PDRG1", "MRPL33", "RPS27", "TUBA1A", "TRIM28", "EEF1A2", "ARMCX6", "GAR1", "TOMM7", "POLR2I", "TMEM14A"], "H3K4me3_keratinocyte_hg19": ["CDKN1A", "CRABP2", "C2ORF47", "NDUFB11", "SRRT", "TAF9", "TOB1", "DCAF6", "UBL5", "TRIM28", "CREG1", "ATP5D", "STRA13", "MOAP1", "G6PD", "NIPSNAP3A", "NDUFA4", "C14ORF119", "RBM18", "FAM103A1", "ALG2", "TBCC", "PTRHD1", "MESDC1", "RPS25", "PSMC4", "RAB13", "LAP3", "ANKRA2", "SRSF6", "TP53"], "H3K4me3_bone marrow macrophage_mm9": ["HES6", "NOP58", "NMB", "ANAPC15", "CRABP2", "CCDC115", "PRKCSH", "GTF3C6", "NRARP", "NME4", "GLRX2", "PDRG1", "MRPL33", "CS", "TUBA1A", "TRIM28", "PPDPF", "SEC61G", "RAB13", "TMEM14A", "UBQLN2"], "H3K4me3_H1-hESC_hg19": ["MOAP1", "NMB", "NDUFB11", "NCBP2", "YIPF3", "RBM18", "FAM103A1", "ALG2", "USMG5", "TRIAP1", "THAP10", "UBL5", "RPS25", "NSA2", "PSMC4", "CREG1", "PPDPF", "C11ORF48", "PIGF"], "H3K4me3_liver_mm9": ["ANAPC15", "PRKCSH", "GTF3C6", "CISD1", "TRIAP1", "MRPL33", "TUBA1A", "TRIM28", "SEC61G", "GAR1", "SH3BGRL3", "POLR2I", "TMEM14A", "KLF10", "NMB", "CCDC115", "RBM18", "MRPL49", "NME4", "UBE2A", "PDRG1", "CS", "RPS27", "RAB13", "ARMCX6", "MYD88"], "H3K4me1_A549_hg19": ["GRN", "MAGED1", "GTF3C6", "SLC1A5", "PGRMC1", "RPL36", "FAM53C", "TMEM14A", "S100A11", "BCAS2", "POLR2K", "DCXR", "NDUFC2", "ISG15", "LSR", "GLRX2", "KRT10", "ACYP1", "NBPF15", "RPS27", "RAB13", "ARMCX6", "PPT1", "MAGED2", "OCIAD2", "TP53", "MYD88"], "H3K9ac_A549_hg19": ["HES6", "NMB", "CBX4", "NDUFB11", "SLC10A3", "ISG15", "COX7A2", "NBPF11", "C9ORF78", "MEA1", "EIF2S1", "ZWINT", "PTRHD1", "MZT2A", "PSMC4", "CREG1", "PPDPF", "STRA13", "PIGF"], "H3K9ac_ES-E14_mm9": ["KLF10", "NIPSNAP3A", "CBX4", "PET100", "NDUFA4", "RBM18", "FAM103A1", "RPS27L", "EDF1", "TRIAP1", "COMMD6", "PTRHD1", "EIF1", "DNAJA1", "RAB13", "SRSF2", "PHLDA2", "BCAS2", "TPT1"], "H3K4me2_A549_hg19": ["CRABP2", "TAF9", "COX7A2", "C9ORF78", "MEA1", "UBL5", "PMAIP1", "C11ORF48", "POLR2I", "ARRDC4", "MOAP1", "ZNF263", "C14ORF119", "RBM18", "SLC10A3", "ALG2", "USMG5", "ISG15", "ACYP1", "FOS", "SLC50A1", "ZWINT", "PTRHD1", "RPS25", "MZT2A", "PPDPF", "LOC100129361"], "H3K4me1_lung_mm9": ["MOAP1", "CDKN1A", "NMB", "HSP90AA1", "ANAPC15", "EDF1", "ACYP1", "MLF2", "QARS", "UQCRQ", "ATP5E", "GNPNAT1", "PMAIP1", "SFN", "MAGED2", "STRA13", "PHLDA2", "ANKRA2", "POLR2K"], "H3K4me2_keratinocyte_hg19": ["HES6", "CRABP2", "C14ORF119", "RBM18", "TAF9", "USMG5", "NRARP", "TRIAP1", "SRP14", "SUMF2", "ZWINT", "DCAF6", "UBL5", "RPS25", "RUSC1", "CCNG1", "C11ORF48", "LOC100129361", "STRA13", "NACAP1"], "H3K4me3_heart_mm9": ["PRKCSH", "NDUFB11", "GTF3C6", "NDUFB3", "CISD1", "SEPW1", "MEA1", "MRPL32", "MRPL33", "TRIM28", "SEC61G", "PMAIP1", "TMEM14A", "HSPA8", "NOP58", "NMB", "CCDC115", "RBM18", "DCXR", "NME4", "GLRX2", "UBE2A", "SIRT7", "PDRG1", "CS", "EBNA1BP2", "RPS27", "EEF1A2", "RAB13", "OCIAD2", "MYD88"], "H3K4me2_B cell_hg19": ["NMB", "CRABP2", "YIPF3", "RBM18", "DYNLT3", "TAF9", "ALG2", "LSR", "SPATA20", "SRP14", "EIF2S1", "PTRHD1", "UBL5", "RPS25", "UQCRQ", "CREG1", "PABPC3", "LOC100129361", "STRA13", "POLR2K"], "H3K4me3_SK-N-SH_hg19": ["SF3B4", "NMB", "G6PD", "NIPSNAP3A", "C2ORF47", "CCDC115", "GTF3C6", "TAF9", "EDF1", "THAP10", "TRIM28", "QARS", "EEF1A2", "RAB13", "PPT1", "IRF7", "C11ORF48", "SH3BGRL3", "LAP3", "NUDT15"], "H3K4me1_MEL cell line_mm9": ["MTCH1", "BTG2", "ANAPC15", "EI24", "ZFAND2A", "SEPW1", "SLC1A5", "MEA1", "DCAF6", "CST3", "UBL5", "TUBA1A", "CREG1", "PIP4K2C", "TMEM14A", "IER5", "BCAS2", "IER2", "MOAP1", "GDF15", "YIPF3", "DYNLT3", "TMA7", "TBCC", "GLRX2", "ACYP1", "SUMF2", "PDRG1", "EIF1", "RPS27", "PKM", "UQCRQ", "RAB13", "IRF7", "RPP21", "GLA", "SLU7"], "H3K4me3_bone marrow_mm9": ["NMB", "CCDC115", "NDUFA4", "PRKCSH", "GTF3C6", "RBM18", "CISD1", "MRPL49", "SEPW1", "GLRX2", "TRIAP1", "SMG8", "PDRG1", "MRPL33", "RPS27", "TUBA1A", "TRIM28", "SEC61G", "ARMCX6", "SH3BGRL3", "OCIAD2", "POLR2I"], "H3K4me2_mammary epithelial cell_hg19": ["HES6", "MOAP1", "CRABP2", "YIPF3", "C14ORF119", "ALG2", "USMG5", "ISG15", "NME4", "C9ORF78", "ZWINT", "DCAF6", "UBL5", "MAFB", "PSMC4", "EEF1A2", "C11ORF48", "PABPC3", "STRA13", "NACAP1"]}