{"H2AFZ_GM12878_hg19": ["CHIC1", "PKDCC", "DIRAS2", "PCDHGB2", "PTPN21", "MTMR9", "FAH", "HS3ST1", "COIL", "TOM1L2", "PPP2R3C", "TDG", "METTL20", "LIN52"], "H2AFZ_astrocyte_hg19": ["CCDC167", "UVRAG", "CSF2", "USP53", "IFT172", "DIRAS2", "PCDHGB2", "MTMR9", "CDYL2", "NKAPL", "ACTR3C", "TDG", "ENPP4", "KBTBD8"], "H3K27ac_astrocyte_hg19": ["CCDC167", "UVRAG", "IFT172", "SLC7A11", "PLXDC2", "ZBTB5", "PDIK1L", "PPP2R3C", "ARMC3", "FABP7", "SSBP1", "RBM45", "IL13RA2", "ZNF333", "LIN52"], "H2AFZ_mammary epithelial cell_hg19": ["USP53", "DIRAS2", "PCDHB15", "KCTD4", "PAFAH2", "CDYL2", "MMP10", "NKAPL", "COIL", "SHE", "SERP1", "TTPA", "TDG", "ENPP4", "DCP2"], "H3K9me1_K562_hg19": ["LIPT1", "DET1", "UVRAG", "SLC36A2", "EGF", "IFT172", "EXOC6B", "FAH", "PAFAH2", "LENEP", "SAMD15", "VGF", "PPP2R3C", "CLPTM1", "DCP2"], "H3K27ac_ES-E14_mm9": ["SMIM13", "ZYG11A", "USP53", "AGPAT9", "KLHL15", "RNF8", "MTMR9", "SLC7A11", "EPRS", "PLXDC2", "RABGGTA", "CDYL2", "PDIK1L", "PPP2R3C", "EOGT", "SLC25A22"], "H3K4me2_GM12878_hg19": ["LIPT1", "MMAA", "EGF", "IFT172", "DIRAS2", "NR1I2", "PTPN21", "CDYL2", "COIL", "SLC4A8", "SHE", "SERP1", "IRAK2", "ARMC3", "TTPA", "RPL23AP82"], "H3K27ac_T-cell acute lymphoblastic leukemia_hg19": ["DET1", "CHIC1", "MMAA", "KLRB1", "SLC7A11", "ZBTB5", "GLB1L2", "COIL", "SERP1", "PPP2R3C", "TDG", "RPL23AP82", "SSBP1", "HIF1AN", "STK32B", "ZNF333"], "H3K27me3_A549_hg19": ["TMEM132D", "ANKRD34B", "CLSTN2", "KRTAP9-3", "DDX25", "PTPN21", "MTIF3", "PLXDC2", "HS3ST1", "MMP10", "NKAPL", "SCUBE3", "SPATA16", "TMEM213", "SLC9A5", "PITPNM3", "FGF19", "SLCO2A1", "SCG2", "DSC2"], "H3K4me1_thymus_mm9": ["ANKRD34B", "PKDCC", "CLSTN2", "MEGF11", "SLC41A3", "ABCC9", "ISL1", "SH3YL1", "FAM167A", "PARD6B", "TCN2", "ZMAT3", "TTLL11", "KCNJ2", "LIN52"], "H3K27ac_A549_hg19": ["UVRAG", "TIGD4", "MMAA", "COL11A1", "IFT172", "DCUN1D3", "DIRAS2", "RFTN1", "SIRT4", "GDPD3", "FAH", "HS3ST1", "LENEP", "COIL", "FAM167A", "TCN2", "PPP2R3C", "ARMC3", "FGF19", "SSBP1", "KPNA5", "STK32B", "SLC22A11"], "H3K27me3_GM06990_hg19": ["SCUBE3", "USP43"], "H3ac_C2C12_mm9": ["SMIM13", "USP53", "AGPAT9", "KLHL15", "IFT172", "SIRT4", "PTPN21", "PRDM1", "FAH", "RABGGTA", "SH3YL1", "FAM195B", "CLPTM1", "TTLL11", "ASB5", "GABPA"], "H3K4me3_cortical plate_mm9": ["BCAR3", "PCDHGB2", "PTPN21", "ABCC9", "PCTP", "RABGGTA", "NKAPL", "GLB1L2", "TCN2", "TTPA", "METTL20", "FAM150B", "SCG2", "STK32B", "GABPA"], "H4K20me1_fibroblast of lung_hg19": ["CSGALNACT1", "CLSTN2", "MEGF11", "SLC3A1", "GLB1L2", "SLC4A8", "TOM1L2", "SCUBE3", "SERP1", "CLPTM1", "NDP", "RBM45", "SLC25A22", "ST3GAL2", "GABPA"], "H3K4me2_T-cell acute lymphoblastic leukemia_hg19": ["CCDC167", "LIPT1", "DET1", "MMAA", "PCDHGB2", "PRDM1", "RABGGTA", "TOM1L2", "FAM167A", "TMEM17", "FAM195B", "SFXN4", "SCG2", "STK32B", "LIN52"], "H3K4me1_MEL cell line_mm9": ["CCDC167", "CSF2", "DDX25", "KLHL15", "IFT172", "DCUN1D3", "RNF8", "GDPD3", "SLC7A11", "MTIF3", "LMOD3", "NKAPL", "ATAD2B", "IRAK2", "TDG", "FAM198B", "ENPP4", "SLC25A22", "PRKAB2", "HSD3B1", "EXOC6B", "F2", "KCTD4", "RABGGTA", "FA2H", "SLC4A8", "SH3YL1", "VGF", "TREML4", "S100A4", "KBTBD8", "DSC2"], "H3K4me3_CH12.LX_mm9": ["CCDC167", "LIPT1", "AMER3", "AGPAT9", "KLHL15", "IFT172", "DCUN1D3", "SLC41A3", "PTPN21", "MTMR9", "NKAPL", "PARD6B", "CLPTM1", "ENPP4", "GABPA", "LIN52", "CSGALNACT1", "PRKAB2", "MMAA", "USP43", "SIRT4", "PCDHB15", "RABGGTA", "HS3ST1", "CDYL2", "SLC4A8", "TOM1L2", "SH3YL1", "SLC9A5", "TCN2", "SSBP1", "KBTBD8"], "H3K4me3_mononuclear cell_hg19": ["PRKAB2", "TIGD4", "CRADD", "USP53", "AGPAT9", "MMAA", "IFT172", "PCDHGB2", "ZBTB5", "PARD6B", "PPP2R3C", "TDG", "SFXN4", "ENPP4", "ZNF333"], "H3K4me3_T-cell acute lymphoblastic leukemia_hg19": ["LIPT1", "DET1", "CHIC1", "PCDHGB2", "RABGGTA", "TOM1L2", "FAM167A", "TMEM17", "PPP2R3C", "TDG", "SFXN4", "SCG2", "STK32B", "ZNF333"]}