{"GABPA_HL-60_hg19": ["DCLRE1B", "PRPF6", "DDX11", "NUF2", "NUCB1", "TSNAX-DISC1", "LRIF1", "LINC00339", "MCAT", "SUPT6H", "HSP90B1"], "EP300_GM12878_hg19": ["ST6GALNAC1", "PRUNE", "GMPR", "SLC2A3", "PLD6", "SUPT6H", "LOC642846", "KCTD20", "NUF2", "ORMDL3", "MXI1", "JUNB", "FCRL5", "LOC642236", "G0S2", "TEKT4P2", "HIST2H2BE", "EHD3", "PRPF6", "PPIF", "NUCB1", "LRIF1", "CD101", "BAP1", "TMEM45A"], "POLR2A_GM19193_hg19": ["IFT88", "GSTM1", "IL7", "LOC220729", "NUF2", "R3HDM4", "CHAC2"], "CHD2_GM12878_hg19": ["RIC3", "FIP1L1", "ZNF480", "PRUNE", "G0S2", "BAP1", "NRGN"], "RELA_GM18951_hg19": ["NUF2", "SNHG9", "IER3"], "POLR2A_MEL cell line_mm9": ["KDM5D", "PROS1", "PRUNE", "PLD6", "TNF", "TRIOBP", "HSP90B1", "NUAK2", "PRKAR2B", "UAP1L1", "ORMDL3", "MXI1", "PLEK2", "TBC1D10B", "IER3", "USP46", "PPP1R14A", "ABCC4", "SLMO2", "GSTM1", "JUP", "BIK", "TPM1", "TTC7B", "PLA2G4A", "GP5", "ASRGL1", "DEPDC7", "IFT88", "TEC", "TMEM158", "R3HDM4"], "POLR2A_GM12891_hg19": ["RIC3", "CCDC58", "RPS4Y1", "MCAT", "CORO1C", "IFT88", "FIP1L1", "NUF2", "MXI1", "CHAC2", "TSNAX-DISC1", "GRAP", "LRIF1", "JUNB"], "POLR2A_GM12878_hg19": ["PRUNE", "CSF2RB", "SLC2A3", "NID1", "CORO1C", "LOC642846", "FIP1L1", "LOC220729", "NUF2", "UAP1L1", "CHAC2", "KCNN4", "JUNB", "MORC2", "IER3", "USP46", "RIC3", "SLMO2", "GSTM1", "JUP", "EIF2AK1", "CCDC58", "ELOVL7", "ZNF57", "MCAT", "CKAP4", "NET1", "DEPDC7", "IFT88", "TEC", "R3HDM4", "GRAP", "TMEM45A"], "RELA_GM15510_hg19": ["ABCC4", "NUF2", "PPIF", "TSNAX-DISC1", "IER3"], "EGR1_GM12878_hg19": ["PARM1", "ZNF480", "ITGB3", "CCDC58", "SNHG9", "MCAT", "SUPT6H", "STRN4", "C9ORF41", "IFT88", "SESN3", "NUF2", "SEC14L5", "JUNB", "EIF4G1"], "CEBPB_HepG2_hg19": ["PROS1", "CRISP3", "HP", "HPR", "NID1", "ZNF57", "HIST2H2BE", "TP53I3", "KCTD20", "TCN1", "PPIF", "MANSC1", "S100P", "TSNAX-DISC1", "ZNF711", "LRIF1", "MEST", "ABCG1", "CES1", "IER3"], "ATF3_A549_hg19": ["MZT2A", "JUN", "NUF2", "SNHG9", "JUNB", "HSP90B1", "CYB5D1", "IER3"], "POLR2A_GM12892_hg19": ["RIC3", "ABCC4", "SLMO2", "IFT88", "GSTM1", "BIK", "LOC220729", "CCDC58", "NUF2", "TSNAX-DISC1", "MCAT", "MYL9"], "POLR2A_NB4_hg19": ["IFT88", "LOC220729", "EIF2AK1", "R3HDM4", "S100P", "MCAT"], "SIX5_A549_hg19": ["EHD3", "PRPF6", "CCDC58", "ORMDL3", "PDIA5"], "POU2F2_GM12878_hg19": ["CR1", "NUF2", "MCAT", "CORO1C"], "GABPA_GM12878_hg19": ["RIC3", "EHD3", "PRPF6", "CTTN", "DDX11", "NUF2", "PRUNE", "TSNAX-DISC1", "MCAT", "LOC642846"], "ZBTB33_A549_hg19": ["DCLRE1B", "PRPF6", "DDX11", "NUF2", "SNHG9", "TSNAX-DISC1", "GTPBP2", "CYB5D1", "IER3"], "EP300_H1-hESC_hg19": ["DCLRE1B", "GRB14", "PRKAR2B", "BIK", "LGALSL", "MANSC1", "ELOVL7", "NID1", "HRASLS", "MCAT", "HIST2H2BE", "CORO1C"], "ELF1_SK-N-SH_hg19": ["PRPF6", "ZNF480", "NUF2", "LRIF1", "JUNB", "SUPT6H", "BAP1"]}