{"CHD7_H1-hESC_hg19": ["RPL30", "SQRDL", "PTGS2", "UBE2Z", "IFIT1", "EEF1B2", "RPS3", "EPSTI1", "NDUFA9", "HS3ST3B1", "PNPT1", "H3F3B", "GCH1", "RIPK2", "IL10RA", "LIMK2", "MX1", "ISG15", "PARP14", "PSMA6", "RNF144B", "RPS29", "DNAJB11", "CMPK2", "TGFBI"], "CTCF_lung_hg19": ["CD80", "SPPL2A", "UBE2L6", "CBWD1", "IFI35", "UBE2Z", "RASGRP1", "FUT4", "PSMD8", "SEC61G", "RPS3", "SH3BGRL3", "DENND5A", "RBM34", "IL15RA", "OST4", "MREG", "PNPT1", "SP110", "DDX58", "ADPRHL2", "ACSL1", "ISG15", "MANF", "NFKBIA", "MYL6", "SPECC1L"], "MYC_NB4_hg19": ["TNFAIP6", "GTF2B", "FPR1", "DEFB1", "SQRDL", "TXN", "DDX60", "ACTG1", "RPS16", "TMSB4X", "C3AR1", "STOM", "SH3BGRL3", "TIMP1", "GBP2", "TMSB10", "RPL39", "SP110", "DDX58", "ISG15", "IL1B", "OAS3", "DDIT4", "PSME1", "AIDA", "S100A8"], "ESRRA_HepG2_hg19": ["TP53INP2", "SOD2"], "MAX_A549_hg19": ["PI4K2B", "CD274", "CLIC4", "GTF2B", "SPPL2A", "FAM129A", "AKR1B1", "DDX60L", "SQRDL", "RASGRP1", "SAT1", "CXCL5", "FUT4", "HERC5", "RPS16", "BASP1", "STOM", "CTSH", "TIMP1", "RPL39", "RPS12", "IER3", "HS3ST3B1", "ACOT9", "OST4", "TIMMDC1", "DYNLT1", "DDX58", "LIMK2", "LAMB1", "TNFRSF1B", "TOR1B", "PARP9", "CKAP4", "ATOX1", "C15ORF48", "PSMA6", "RNF144B", "PSMA1", "OAS3", "CMPK2", "B4GALT5"], "MAX_H1-hESC_hg19": ["RPL30", "B4GALT1", "GTF2B", "AMD1", "UBE2L6", "ADAR", "DDX60L", "PTGS2", "UBE2Z", "CXCL5", "FUT4", "ACTG1", "PSMD8", "PSMB4", "MT2A", "RPS16", "TMSB4X", "STOM", "SH3BGRL3", "RBM34", "RPL39", "CD55", "HS3ST3B1", "ACOT9", "WSB1", "TIMMDC1", "CCL20", "RPS8", "STAT2", "LIMK2", "PARP9", "CKAP4", "PSMA6", "RNF144B", "BCL6", "PPA1", "RPS29", "SMS", "RGL1", "DLD"], "RXRA_SK-N-SH_hg19": ["ANXA2", "VIM", "IER3"], "MEF2C_GM12878_hg19": ["LMO2", "CCL3", "AKR1B1"], "TBP_K562_hg19": ["CD40", "CLIC4", "SAMD9", "SAT1", "ACTG1", "EEF1B2", "RPS16", "PSTPIP2", "BAG1", "NFKBIZ", "CTSH", "RBM34", "LYN", "MREG", "PNPT1", "SP110", "RPS8", "STAT2", "G0S2", "TOR1B", "ATOX1", "VAV1", "PSMC6", "CD47", "AIDA", "KPNB1"], "POLR2A_Raji_hg19": ["CLIC4", "IFI6", "RNF19B", "ADAR", "SNX10", "TXN", "PLAC8", "SLAMF7", "IER3", "LYN", "SRGN", "ACOT9", "H3F3B", "DYNLT1", "STAT2", "LIMK2", "COX6B1", "PSMA6", "MYL6", "PSMA4", "RPS29", "DDIT4", "NINJ1", "DNAJB11", "KIAA0247", "PLEKHO2"], "GABPA_MEL cell line_mm9": ["FTH1", "UBC", "CXCL5"], "E2F4_myocyte_mm9": ["CLIC4", "CBWD1", "HIF1A", "IFIT2", "TUBB6", "RPS16", "NBN", "OST4", "MREG", "WSB1", "TIMMDC1", "RPS8", "ADPRHL2", "EDEM1", "STAT2", "SOD2", "CXCL10", "MARCKS", "NAGK", "DNAJB11", "SPECC1L", "VIM", "BLVRA", "PFKP", "FKBP5"], "REST_HL-60_hg19": ["ANXA5", "DNAJB11"], "POLR2AphosphoS2_K562_hg19": ["UFD1L", "PI4K2B", "CD40", "IFITM2", "GTF2B", "AQP9", "GMPR", "LOC284454", "IFI35", "FPR2", "RASGRP1", "PSMD8", "UGCG", "TUBB6", "MT2A", "RPS16", "PSTPIP2", "ORMDL2", "SEC61G", "STOM", "CCL2", "BID", "SRGN", "IL15RA", "ACOT9", "OST4", "SSB", "PNPT1", "GCH1", "RIPK2", "DDX58", "ACSL1", "EDEM1", "IL10RA", "ANXA5", "G0S2", "NR1H3", "TNFRSF1B", "TOR1B", "PARP14", "ATOX1", "COX6B1", "HCK", "PPA1", "NINJ1", "CD47", "PFKP", "TLR2"], "ZNF143_HeLa-S3_hg19": ["CD274", "CLIC4", "RPL30", "B4GALT1", "CNP", "RPL34", "GTF2B", "ADAR", "SQRDL", "UBE2Z", "SAT1", "PSTPIP2", "TP53INP2", "NAMPT", "RBM34", "NDUFA9", "OST4", "WSB1", "TIMMDC1", "ADPRHL2", "STAT2", "MX1", "PSMC6", "PPIF", "CD44", "BLVRA", "S100A8"], "MAX_HeLa-S3_hg19": ["CD274", "RPL30", "B4GALT1", "RPL32", "UXS1", "RPL34", "GTF2B", "IFI6", "ADAR", "DEFB1", "TXN", "TMEM140", "UBE2Z", "HIF1A", "IFIT3", "EEF1B2", "HERC5", "MT2A", "RPS16", "KYNU", "SEC61G", "RPS3", "STOM", "SLC39A8", "TIMP1", "RBM34", "RPL39", "CD55", "RPS12", "MREG", "PNPT1", "TIMMDC1", "RPS8", "LIMK2", "PLA2G4A", "COX6B1", "ISG20", "PSMA6", "NAGK", "SLPI", "OAS1", "RPS29", "IL1B", "DNAJB11", "SRSF2", "S100A8"], "ELK4_HEK293_hg19": ["UFD1L", "B4GALT1", "RPL32", "PTTG1IP", "DDX60", "SAT1", "ACTB", "FUT4", "EEF1B2", "PSMD8", "PSMB4", "RPS16", "UBC", "RPS3", "RBM34", "WARS", "TIMMDC1", "ADPRHL2", "STAT2", "TUBB4B", "COX6B1", "MANF", "EXT1", "MTF1", "PFN1"], "CTCF_kidney_hg19": ["IFITM2", "RPL32", "GTF2B", "UBE2L6", "ADM", "IFI35", "UBE2Z", "RASGRP1", "FUT4", "RPS16", "RPS3", "SH3BGRL3", "NBN", "NDUFA9", "OST4", "MREG", "WARS", "DYNLT1", "SP110", "DDX58", "ACSL1", "TUBB4B", "NFKBIA", "RNF144B", "MYL6", "RPS29", "SPECC1L"], "USF1_A549_hg19": ["PI4K2B", "CD63", "HIST2H2AA4", "GTF2B", "ADAR", "IFI35", "TXN", "PTGS2", "HIF1A", "ACTG1", "EEF1B2", "HERC5", "PSMD8", "RPS16", "NAMPT", "STOM", "ST3GAL5", "NDUFA9", "PNPT1", "WSB1", "WARS", "RPS8", "ADPRHL2", "STAT2", "TUBB4B", "ISG20", "TMEFF2", "NAGK", "PSMA4", "BCL6", "PPA1", "RPS29", "DDIT4", "LAP3", "RGL1", "KPNB1"], "CTCF_GM10248_hg19": ["CD274", "IFITM2", "CD80", "SNX10", "IFI35", "PTGS2", "UBE2Z", "RASGRP1", "FUT4", "PSMD8", "KYNU", "SH3BGRL3", "DENND5A", "NBN", "TMSB10", "IL15RA", "OST4", "MREG", "ADPRHL2", "NFKB1", "NFKBIA", "C15ORF48", "HCK", "PPIF", "PSME1"]}