{"POLR2A_GM18505_hg19": ["IFITM1", "HILPDA", "FBXO46", "SLC29A1"], "ZC3H11A_K562_hg19": ["OCA2", "SYCE2", "WDR25", "DRAM1", "SLC29A1", "TMEM231"], "SRF_GM12878_hg19": ["WDR25", "NFIL3", "NCF4", "SRSF2", "TMEM231", "ADAT2"], "GABPA_CH12.LX_mm9": ["WDR25", "FBXO46", "ARHGAP26", "DNAJC28"], "POLR2A_K562_hg19": ["CDKN1C", "IFITM1", "ZCCHC10", "HILPDA", "FAM122B", "MFSD9", "CSRP2", "PTTG1", "EFHD2", "SOSTDC1", "CCDC51", "ARRDC2", "KRT8", "FTSJ2", "MLF1", "MYL4", "LARS2", "COL8A2", "SRSF2", "STEAP1", "SLC29A1", "SKIV2L2", "CAMK2D", "HS3ST3A1", "RGS16", "PTGER3", "SHOX2", "CXCR4", "DNAJC28", "SYCE2", "DRAM1", "NFIL3", "ESD", "PMAIP1", "RHPN2", "HIST1H3B", "TCFL5", "FZD1", "ZFHX2", "TIMMDC1", "DKKL1", "KLF4", "TMEM231", "BAIAP3", "LRG1", "P4HA2", "GNB4", "PTPN4", "MCU", "YPEL2"], "POLR2A_GM12891_hg19": ["TIMMDC1", "APAF1", "ARRDC2", "CXCR4", "FBXO46", "MFSD9", "SYCE2", "PTTG1", "EFHD2", "UGGT2", "SLC29A1", "SKIV2L2", "MCU"], "MAX_K562_hg19": ["HS3ST3A1", "TIMMDC1", "RGS16", "DKKL1", "KRT8", "B3GALT6", "DNAJC28", "ITPRIPL2", "SYCE2", "LARS2", "CSRP2", "CCNE2", "CDHR1", "SYT10", "MEST", "ALOXE3", "MCU", "TCFL5", "CCDC51"], "NFE2_GM12878_hg19": ["LRG1", "B3GALT6", "HIST1H3B", "TMEM91", "MCU", "ADAT2"], "JUND_HepG2_hg19": ["ZFHX2", "TIMMDC1", "DKKL1", "KRT8", "ALG13", "TMEM91", "MLF1", "F5", "C3", "PKIB", "TTR", "HOOK2", "HIST1H3B"], "HCFC1_ES-E14_mm9": ["HS3ST3A1", "FIGN", "RHPN2", "HAP1", "ARHGAP26", "CPLX3"], "YY1_K562_hg19": ["LARS2", "ZCCHC10", "HOOK2", "ARRDC2", "B3GALT6", "PTPN4", "STEAP1", "FTSJ2", "MCU", "ADAT2"], "POLR2A_GM12878_hg19": ["CDKN1C", "IFITM1", "PGAP1", "ZCCHC10", "RGS16", "HILPDA", "CXCR4", "FBXO46", "SHB", "MFSD9", "SYCE2", "CSRP2", "NFIL3", "EFHD2", "PMAIP1", "UGGT2", "TCFL5", "CCDC51", "FZD1", "EGLN3", "TIMMDC1", "GPX3", "ARRDC2", "MIIP", "FTSJ2", "SSTR2", "TMEM231", "ADAT2", "GALC", "LARS2", "LRG1", "P4HA2", "HAP1", "SLC29A1"], "E2F4_myocyte_mm9": ["CSRP2", "TIMMDC1", "APAF1", "SOX11", "FBXO46", "KLF4", "FTSJ2"], "POLR2A_GM18951_hg19": ["ZFHX2", "PTTG1", "HILPDA", "SHB", "SLC29A1", "ARHGAP26"], "GABPA_HepG2_hg19": ["MFSD9", "WDR25", "TIMMDC1", "FBXO46", "FTSJ2", "CCDC51", "ADAT2"], "USF1_A549_hg19": ["FZD1", "CAMK2D", "WDR25", "PPP1R3B", "ARRDC2", "B3GALT6", "FBXO46", "MLF1", "CCDC51", "ADAT2"], "MYC_K562_hg19": ["CDKN1C", "OCA2", "ZCCHC10", "HS3ST3A1", "RGS16", "PTGER3", "HILPDA", "FBXO46", "SHB", "DNAJC28", "CPLX3", "FAM122B", "SYCE2", "DRAM1", "PTTG1", "ESD", "EFHD2", "SOSTDC1", "UGGT2", "MEST", "ALOXE3", "CCDC51", "TIMMDC1", "ARRDC2", "DKKL1", "HPCAL1", "KRT8", "ALG13", "B3GALT6", "FTSJ2", "F5", "ADAT2", "C1QL1", "LARS2", "EHD4", "LRG1", "CCNE2", "P4HA2", "COL6A2", "EHBP1L1", "GNB4", "SRSF2", "RBM20", "PTPN4", "SLC27A2", "MRAP2", "SKIV2L2", "MCU"], "POLR2A_Raji_hg19": ["FZD1", "PGAP1", "ZCCHC10", "ARRDC2", "NCF4", "HILPDA", "DNAJC28"], "USF2_HepG2_hg19": ["WDR25", "SRSF2", "DEFB1", "MLF1", "ADAT2"], "GABPA_HeLa-S3_hg19": ["PKIB", "WDR25", "TIMMDC1", "KRT8", "ALG13", "FTSJ2", "UGGT2", "CCDC51", "ADAT2"]}