{"H3K4me3_B cell_hg19": ["NDUFA11", "HSD17B4", "YBX1", "CSAD", "NID2", "UQCRH", "HSPD1", "MARC2", "MARC1", "PDK4", "UQCRFS1", "NDUFV2", "SH2B2", "TMEM14C", "PDHX", "G6PD", "NDUFA3", "BNIP3", "PGAM1", "ELOVL6", "NFATC4", "NUDT7", "ACOX1", "CAT", "NDUFS3", "ACO2", "SLC25A5"], "H3K4me3_HepG2_hg19": ["CFD", "NDUFB9", "MOCS2", "ABCD2", "NDUFA11", "NDUFB3", "UQCR11", "CSAD", "NID2", "MARC2", "PDK4", "STOM", "UQCRFS1", "NDUFV1", "GLUL", "IDH3A", "TIMM8B", "PDHA1", "MDH1", "PGAM1", "PPP2R5A", "USMG5", "ELOVL6", "SDHD", "PODN", "COX6C", "NUDT7", "PC", "RRAGC", "NDUFS5", "ALB", "ECHDC1", "OGDH"], "H3K27ac_mammary epithelial cell_hg19": ["MOCS2", "G6PD", "ACAA2", "RETSAT", "MDH2", "NDUFA4", "IDH3G", "NDUFA1", "UQCR11", "UQCR10", "COX5B", "ACACA", "QDPR", "LDHA", "SAMM50", "ACOX1", "PSAT1", "ATP5E", "CAT", "NDUFS2"], "H3K4me3_bone marrow macrophage_mm9": ["NDUFB6", "DGAT1", "IDH3G", "ECH1", "MGST1", "NDUFA1", "CIDEA", "ETFB", "DNAJC15", "FAM213A", "AGPAT2", "CAR5B", "CS", "LDHB", "PXMP2", "KDR", "PDK4", "CCDC3", "HADH", "NDUFV2", "IDH3A"], "H3K4me1_GM12878_hg19": ["MDH1", "TSC22D3", "ATP5A1", "MGST2", "CHCHD10", "ETFA", "AGPAT2", "NID2", "CPT1B", "NFATC4", "ATP5J2", "FABP3", "LGALS1", "CPT2", "RDH11", "MARC2", "ACO1", "SLC25A10", "SH2B2", "PDK1"], "H3K9me3_K562_hg19": ["TIMM8B", "HMGCS1", "NDUFA12", "NDUFA3", "ATP5C1", "HSD17B4", "NDUFC1", "COX7A2", "SDHD", "COX6C", "CSAD", "ATP5J2", "HADHB", "HADHA", "LDHB", "ATP5B", "AUH", "CAT", "STOM", "UQCRC2", "TMEM14C"], "H3K4me1_heart_mm9": ["NDUFA12", "INSIG1", "AQP7", "ATP1A2", "ETFA", "TMEM140", "GM2A", "APMAP", "MARC1", "IDH3B", "PHGDH", "SCD1", "SH2B2", "ADIG", "CAR3", "GRCC10", "NDUFA3", "EPHX2", "CIDEA", "CYP4B1", "CHCHD10", "MIF", "CMBL", "ATP5F1", "DNAJC15", "FAM213A", "ATP5J2", "RBP4", "FABP4", "UQCRQ", "PSAT1", "COL5A3", "PXMP2", "ECHDC1", "ALDOA"], "H3K27me3_NT2-D1_hg19": ["FAM57B", "TSC22D3", "EPHX2", "AQP7", "HBA1", "PODN", "COX6C", "AGPAT2", "ACAT1", "RBP7", "LIPE", "ACADL", "COL5A3", "ATP5D", "PLIN4", "TSPO", "HADH", "MGLL", "PHLDA3"], "H3K4me3_cardiac mesoderm_hg19": ["NDUFA11", "NDUFB3", "COX7A2", "COX5B", "CSAD", "UQCRH", "LDHA", "ACADL", "CPT2", "MARC2", "ME1", "UQCRFS1", "NDUFV2", "GLUL", "PHLDA3", "G6PD", "MDH1", "IDH1", "TSC22D3", "PGAM1", "PPP2R5A", "SDHC", "PODN", "FAM213A", "NFATC4", "FABP3", "PC", "STAR", "UQCRQ", "ACOX1", "NDUFS5", "NDUFS3", "ECHDC1", "CYCS", "ACO2", "PPIA"], "H3K4me3_HEK293_hg19": ["MOCS2", "G6PD", "MDH1", "NDUFA11", "TSC22D3", "PGAM1", "PPP2R5A", "YBX1", "CSAD", "HADHB", "QDPR", "HADHA", "ACOX1", "COL5A3", "MARC2", "KDR", "ME1", "TKT", "GLUL", "PHLDA3", "DECR1", "TMEM14C"], "H3K4me3_brain microvascular endothelial cell_hg19": ["MOCS2", "DGAT1", "EPHX2", "PGAM1", "PPP2R5A", "ELOVL6", "YBX1", "PODN", "CSAD", "HSPD1", "QDPR", "ACOX1", "MARC2", "MARC1", "KDR", "SLC25A10", "GLUL", "PPIA", "PHLDA3", "PDK1", "IDH3A"], "H3K4me3_A549_hg19": ["NDUFB9", "GPI", "MOCS2", "ABCD2", "NDUFA11", "COX4I1", "DBI", "COX7A2", "UQCR11", "UQCR10", "PDHB", "TMEM140", "AACS", "GM2A", "FTH1", "NDUFV2", "B2M", "PHLDA3", "TIMM8B", "SUN2", "IDH3G", "PGAM1", "USMG5", "ELOVL6", "SDHD", "FAH", "ATP5F1", "FAM213A", "NFATC4", "PC", "RRAGC", "COL5A3", "NDUFS3", "ACO1", "UQCRC2"], "H3K4me2_keratinocyte_hg19": ["TIMM8B", "BCAP31", "POSTN", "COX4I1", "EPHX2", "CHCHD10", "USMG5", "DBI", "UQCR11", "ETFB", "UQCR10", "ATP5F1", "TMEM140", "NFATC4", "RBP4", "SAMM50", "ACOX1", "FASN", "KDR", "PDK4", "UQCRC2", "PDK1"], "H3K27me3_brain_mm9": ["NDUFB9", "PDHA1", "EPHX2", "MGST1", "CIDEA", "CHCHD10", "FAH", "PODN", "FADS3", "FABP3", "UGP2", "ACADL", "KDR", "PDK4", "IRF7", "ME1", "TSPO", "CDO1", "SH2B2", "S100A11", "MGLL", "PHLDA3"], "H3K4me3_liver_mm9": ["NDUFB6", "NDUFA11", "CISD1", "MGST1", "ETFB", "AGPAT2", "APMAP", "RDH11", "PDK4", "NDUFV2", "IDH3A", "CAR3", "PDHA1", "IDH3G", "TSC22D3", "ECH1", "NDUFA1", "VEGFB", "SDHA", "DNAJC15", "FAM213A", "CAR5B", "CS", "ACOX1", "FASN", "GAPDH", "DLD"], "H3K4me3_heart_mm9": ["NDUFB3", "CISD1", "MGST1", "HSD17B12", "TMEM140", "AGPAT2", "LIPE", "APMAP", "RDH11", "KDR", "PDK4", "DECR1", "IDH3A", "PDHA1", "DGAT1", "IDH3G", "IDH1", "ECH1", "NDUFA1", "CIDEA", "CYP4B1", "DNAJC15", "FAM213A", "CAR5B", "CS", "FASN", "PXMP2", "ECHDC1", "ACO1", "GAPDH", "ALDH9A1"], "H3K4me3_astrocyte of the spinal cord_hg19": ["G6PD", "TSC22D3", "PPP2R5A", "CHCHD10", "ELOVL6", "YBX1", "PODN", "CSAD", "NID2", "UQCRH", "ACADL", "ACOX1", "MARC2", "MARC1", "ME1", "ECHDC1", "SLC25A10", "GLUL", "DLD", "PHLDA3"], "H3K4me2_fibroblast of lung_hg19": ["TIMM8B", "GPI", "ABCD2", "MDH1", "NDUFA11", "IDH3G", "EPHX2", "CIDEA", "CHCHD10", "USMG5", "UQCR11", "CPT1B", "LPCAT3", "COL5A3", "IDH3B", "PDK4", "NDUFS1", "CD36", "UQCRC2"], "H3K4me3_kidney_mm9": ["SUN2", "ABCD2", "PDHA1", "NDUFB6", "NDUFA4", "IDH3G", "ECH1", "NDUFA1", "CIDEA", "ETFB", "CMBL", "FAM213A", "AGPAT2", "CS", "APMAP", "RDH11", "FASN", "PXMP2", "PDK4", "HADH", "SH2B2", "IDH3A"], "H3K4me3_small intestine_mm9": ["SUN2", "ABCD2", "PDHA1", "DGAT1", "ECH1", "CIDEA", "CYP4B1", "ETFB", "CMBL", "AGPAT2", "CAR5B", "CS", "APMAP", "RDH11", "FASN", "PXMP2", "KDR", "PDK4", "SH2B2", "IDH3A"]}