{"H3K27ac_A549_hg19": ["ITGA3", "RPP40", "FAM86C1", "ARL2", "FAM86B1", "FAM86C2P", "FAM102B", "TMEM147", "NDUFAF4", "CYP4V2", "HIST1H2BF", "PCDHA4", "HIST1H4C", "RNU4ATAC"], "H3K79me2_myocyte_mm9": ["FUNDC2", "TMEM147", "SSNA1", "NDUFAF4", "SECISBP2", "ID1", "UTP20", "TTC27", "EIF2A", "THOC6"], "H3K9ac_NT2-D1_hg19": ["TMEM147", "TMEM179B", "TYW3", "CYP4V2", "RPP40", "TMEM126A", "PCDHA4", "TTC27", "CUTC"], "H3K9me1_K562_hg19": ["TPD52", "HIST1H2AM", "ANG", "HDDC3", "HIST1H2AC", "TTC27", "FDXACB1", "HIST1H2BC", "HIST1H2AB", "THOC6"], "H3K4me3_astrocyte_hg19": ["FAM102B", "TMEM147", "TYW3", "RPP40", "HIST1H2AJ", "HIST1H2BE", "PCDHB14", "HIST1H2BG", "HIST1H4C", "TTC27", "CUTC"], "H3K9ac_mammary epithelial cell_hg19": ["HIST1H2AM", "HIST1H2BM", "FAM102B", "TMEM147", "NDUFAF4", "ARL2", "HIST1H2BG", "TTC27", "CUTC", "HIST2H2AC"], "H2AFZ_H1-hESC_hg19": ["CCDC167", "HIST1H3A", "SCFD2", "ID1", "RPP40", "TMEM126A", "PCDHB14", "UTP20", "PRKD1", "TTC27", "RIBC2"], "H3K9ac_K562_hg19": ["C17ORF75", "MTFP1", "SSNA1", "SECISBP2", "RPP40", "ARL2", "FAM86B1", "WDYHV1", "FAM104B", "DCAF4", "HIST2H2AC", "FAM102B", "CALB1", "TMEM147", "CYP4V2", "PRKD1", "RNF122", "HIST1H4E"], "H3K4me3_bone marrow macrophage_mm9": ["NT5C", "TYW3", "STX8", "ID1", "HIST1H3F", "RNF122", "RIBC2", "DCP1B", "THOC6"], "H3K36me3_cardiac mesoderm_hg19": ["PRMT6", "MTFP1", "SSNA1", "SECISBP2", "MAZ", "FAM104B", "THOC6", "NT5C", "TRMT112", "TMEM147", "NDUFAF4", "ID1", "C11ORF68"], "H3K4me3_NT2-D1_hg19": ["TMEM147", "HIST3H2A", "HIST1H2AI", "TMEM179B", "TYW3", "HIST1H2AK", "CYP4V2", "RPP40", "FAM104B", "TTC27", "CUTC", "HIST2H2AC"], "H3K4me2_astrocyte_hg19": ["TMEM147", "SSNA1", "CYP4V2", "FAM86C1", "PCDHB14", "ARL2", "HIST1H2BG", "FBLL1", "RNU4ATAC", "RIBC2"], "H3K36me3_K562_hg19": ["HIST1H2BN", "HIST2H2AA3", "TMEM179B", "HIST2H2BC", "THOC6", "TRMT112", "TMEM147", "HIST1H4B", "NDUFAF4", "ID1", "HIST1H3H", "C11ORF68", "HIST1H1C"], "H2AFZ_fibroblast of lung_hg19": ["CCDC167", "DUT", "OSGEPL1", "TYW3", "PCDHB14", "HIST2H2BA", "HIST1H3I", "TTC27", "EIF2A", "TMTC4"], "H3K9me3_ES-E14_mm9": ["DUT"], "H3K4me2_K562_hg19": ["TPD52", "HIST1H2AL", "C17ORF75", "STX8", "RPP40", "FAM86C1", "PCDHB14", "ARL2", "WDYHV1", "C11ORF68"], "H4K20me1_GM12878_hg19": ["NT5C", "H1F0", "ACTR1B", "TMEM179B", "ID1", "MAZ", "HIST1H1E", "H1FX", "HIST1H3H", "ANG", "EIF2A"], "H3K4me3_erythroblast_mm9": ["AADAT", "ATRAID", "TTC27", "TMTC4", "NT5C", "STAG1", "TMEM147", "TMEM126A", "HIST1H2BE", "UTP20", "HIST1H3I", "CUTC", "FDXACB1"], "H3K4me2_A549_hg19": ["HIST1H2AM", "SSNA1", "STX8", "FAM86C1", "PCDHB14", "ARL2", "WDYHV1", "HIST2H2BA", "TMEM147", "CYP4V2", "PRKCDBP", "PCDHA4", "RNU4ATAC"], "H3K4me1_liver_mm9": ["PRMT6", "HIST1H2BN", "DUT", "SFT2D3", "HIST1H2AH", "SSNA1", "RPP40", "ARL2", "METRNL", "HDDC3", "NT5C", "UTP20", "HIST1H2BH", "HIST1H3I", "SLC37A4", "RIBC2", "FDXACB1"]}