{"BL580 (MDC1)": ["TOP2A"], "CBC2152 (RFWD3)": ["TOP2A"], "BL2310 (MLLT3)": ["TOP2A"], "BL5829 (PHF6)": ["TOP2A"], "BL2032 (RFWD2)": ["PATL1"], "BL2031 (RFWD2)": ["PATL1"], "BL5398 (FAM175B)": ["TOP2A"], "SC-197 (MAX)": ["TOP2A"], "a-BRCC36 (BRCC3)": ["TOP2A"], "BL2838 (UIMC1)": ["TOP2A"], "BL1326 (FOXO3)": ["TOP2A"], "BL5619 (DAXX)": ["TOP2A"], "BL4923 (TRIM29)": ["TOP2A"], "BL531 (MCM10)": ["TOP2A"], "BL4102 (PRMT6)": ["TOP2A"], "SC-8002 (ESR1)": ["TOP2A"], "BL2291 (BTBD12)": ["TOP2A"], "BL2512 (TLK2)": ["TOP2A"], "BL2255 (PRKRIR)": ["TOP2A"], "BL5763 (IRS2)": ["TOP2A"]}