{"H3K27ac_A549_hg19": ["POP5", "IFITM2", "RPN2", "HDAC1", "CETN3", "UQCR11", "MSMO1", "PARK7", "PHB", "COX5A", "ATP5G1", "AURKA", "PLAC8", "PPP1CC", "PTDSS1", "ATP5E", "STRA13", "FAM3C", "SNRPD3", "KPNA2", "MYBL1", "TMEM14A", "CTSC", "APLP2", "PBX3", "GGH", "ATP5F1", "TUBB4B", "ZWINT", "PSMC5", "NSA2", "EHD4", "SPCS1", "SNRNP25", "TRIP13", "HIST1H4C", "HNRNPA1L2"], "H3K4me3_HeLa-S3_hg19": ["SET", "ARL6IP1", "HDAC1", "CETN3", "ATP5C1", "PHB", "ATP5G1", "TMEM123", "LAPTM4B", "TUBA1B", "TUBB6", "YWHAQ", "PSMB3", "PLS3", "STRA13", "SNRPD3", "MYBL1", "PHLDA1", "SAC3D1", "S100A10", "HMGN1", "EIF5A", "RANBP1", "SMURF2", "PGAM1", "PBX3", "HMGA2", "NAP1L1", "EMP3", "ATP5F1", "TMEM158", "SPCS1", "TRMT5", "SNRPG", "CKS2", "CDK2AP1", "PTX3", "VIM", "SLIRP", "PFN1", "HIST1H4C", "CALM2", "HNRNPA1L2", "SPC25"], "H2AFZ_skeletal muscle myoblast_hg19": ["HDAC1", "GLDC", "DBI", "TTK", "PHB2", "ATP5G1", "PLAC8", "PRDX4", "RACGAP1", "ATP5E", "WBP5", "AP3S1", "EIF5A", "RANBP1", "DUT", "NPM1", "PLAUR", "CKAP2", "ZWINT", "ATOX1", "DERA", "DHFR", "QARS", "CLNS1A", "SNRPG", "SPC25"], "H3K4me1_heart_mm9": ["IFITM3", "AHCY", "GLDC", "SERPINE1", "BUB1B", "PEBP1", "STC1", "TTK", "PARK7", "PHB", "CDC20", "BLOC1S5", "TUBA1A", "SPP1", "STRA13", "CTNNAL1", "DLGAP5", "DUT", "PLAUR", "TMA7", "GGH", "MIF", "ATP5F1", "NDC80", "ATP5J2", "DERA", "NME1", "DHFR", "FOSL1", "ASPM", "KRT18", "EIF3K", "QARS", "MTHFD1", "AXL", "PPA1", "TRMT5", "CKS2", "PLBD1", "F2RL1", "TRIP13", "ALDOA", "HIST1H4C"], "H3K4me3_limb_mm9": ["IFITM3", "POP5", "CETN3", "RAD51AP1", "CCNB2", "SNRPD2", "YWHAQ", "TUBB3", "NUSAP1", "POLR2I", "TMEM14A", "CLIC1", "S100A10", "EIF5A", "CAV2", "GNG11", "ATOX1", "DERA", "FOSL1", "KRT18", "ADI1", "TRMT5", "MCM3", "PLIN3", "F2RL1", "PSMG2"], "H3K4me3_ES-E14_mm9": ["CDCA3", "CETN3", "ECI2", "DBI", "BZW2", "PHB2", "ACAT2", "CDC20", "RAD51AP1", "UGCG", "NT5E", "TUBB3", "PSMB3", "AP2S1", "STRA13", "SNRPD3", "AP3S1", "RANBP1", "MDH1", "CAV2", "UBE2E3", "CAV1", "APLP2", "PBX3", "TMA7", "GGH", "TUBB4B", "SEPT2", "ZWINT", "PSMC5", "NSA2", "DBF4", "AXL", "RPA3", "TRMT5", "PLBD1", "TRIP13", "STEAP1", "PFN1", "GAPDH"], "H3K9ac_ES-E14_mm9": ["CETN3", "AURKA", "HSP90B1", "CDC20", "UGCG", "PPP1CC", "TMEM123", "NT5E", "TUBB3", "RANBP1", "MDH1", "H2AFZ", "CAV2", "UBE2E3", "IFNGR2", "TUBB4B", "SPCS1", "MTHFD1", "CKS2", "SRSF2", "PLBD1", "TRIP13", "STEAP1", "ALDOA", "CALM2"], "H3K4me3_H1-hESC_hg19": ["MDH1", "CETN3", "MYOF", "DSTN", "GGH", "TTK", "UQCR11", "ATP5I", "PARK7", "PHB", "HMMR", "TUBB4B", "HSP90B1", "HRSP12", "RAD51AP1", "TUBA1C", "PTDSS1", "NSA2", "PPP4R1", "PEG10", "SNRPD3", "SNRPF", "AP3S1", "MYBL1"], "H3K9ac_H1-hESC_hg19": ["SLC20A1", "CETN3", "ATP5I", "PARK7", "PHB", "HMMR", "ACAT2", "HSP90B1", "HRSP12", "PPP1CC", "TUBA1C", "NT5E", "NUSAP1", "RBBP7", "AP3S1", "B2M", "PBX3", "TUBB4B", "ATOX1", "NDC80", "SPCS1", "DDX39A", "EIF3K", "QARS", "PLBD1", "HIST1H4C", "GAPDH"], "H3K4me3_NT2-D1_hg19": ["GLDC", "CETN3", "ATP5C1", "TTK", "UQCR11", "ATP5I", "PARK7", "PHB", "HMGB1", "HMMR", "HRSP12", "LASP1", "PEG10", "AP3S1", "POLR2I", "CEP55", "EIF5A", "ATP5F1", "PSMC5", "SPCS1", "EIF3K", "PRC1", "PLBD1", "TRIP13", "FKBP3"], "H3K9me3_ES-E14_mm9": ["DUT", "CETN3", "HJURP", "SAC3D1"], "H3K4me2_CH12.LX_mm9": ["CAV1", "SERPINE1", "MYOF", "PBX3", "DBI", "TTK", "PHB", "ATP5F1", "BZW2", "ASPM", "LASP1", "PRC1", "CLNS1A", "ID1", "NHP2", "COTL1", "PLIN3", "PSME2", "ITGA6", "STRA13", "VIM", "SNRNP25", "POLR2I", "VCL"], "H3ac_C2C12_mm9": ["PCNA", "CETN3", "ATP5C1", "ATP5H", "BZW2", "ACAT2", "NT5E", "PPP4R1", "PSMB3", "FAM3C", "MYBL1", "B2M", "CLIC1", "RRM2", "CKAP2", "TMA7", "MIF", "NDC80", "DHFR", "PSMA4", "PPA1", "SNRNP25", "TRIP13", "STEAP1", "ALDOA", "GAPDH", "PFN2"], "H3K27me3_HepG2_hg19": ["DNMT1", "TTK", "PARK7", "RAD51AP1", "TMEM123", "LASP1", "PTDSS1", "TUBB3", "WBP5", "CBX5", "H2AFZ", "MYOF", "PLAUR", "GNG11", "NDC80", "ATP5J2", "PSMC5", "NSA2", "PRC1", "CLNS1A", "MCM3", "PLBD1", "HIST1H4C", "CD44", "SLC25A6"], "H3K4me3_SK-N-SH_hg19": ["MCM7", "GLDC", "CDC20", "TMEM123", "LAPTM4B", "NT5E", "YWHAQ", "SPP1", "SNRPD3", "S100A10", "EIF5A", "RANBP1", "DUT", "RPS9", "SMURF2", "PGAM1", "HMGA2", "NAP1L1", "PSMA4", "TMEM158", "SPCS1", "QARS", "MTHFD1", "CKS2", "CDK2AP1", "F2RL1", "PTMA"], "H3K4me3_placenta_mm9": ["SET", "HDAC1", "HSP90B1", "UGCG", "ATP5B", "TUBA1C", "YWHAQ", "PLAU", "NUSAP1", "FAM3C", "TMEM14A", "CLIC1", "FDFT1", "EIF5A", "CBX5", "CAV2", "GGH", "MSN", "ATOX1", "DERA", "DHFR", "PSMC5", "SPCS1", "ADI1", "MCM3", "ITGA6", "MCM6", "STEAP1"], "H3K4me3_A549_hg19": ["AHCY", "IFITM2", "RPN2", "ARL6IP1", "HDAC1", "CETN3", "DBI", "UQCR11", "LOC283683", "PARK7", "PHB", "HMMR", "BZW2", "ATP5G1", "CYR61", "ACAT2", "PLAC8", "RAD51AP1", "NME1-NME2", "TMEM123", "LAPTM4B", "PTDSS1", "SNRPD2", "TUBB3", "SUMO2", "CFL1", "STRA13", "SNRPD3", "B2M", "SAC3D1", "CTSC", "PGAM1", "PBX3", "G0S2", "ATP5F1", "ZWINT", "NME1", "PSMC5", "FABP5", "AXL", "ADI1", "SCD", "STEAP1", "PTMA"], "H3K4me3_endothelial cell of umbilical vein_hg19": ["POP5", "AHCY", "TOMM40", "MCM7", "CETN3", "AMIGO2", "UQCR11", "ATP5I", "LOC283683", "PARK7", "PHB", "YBX1", "ENO1", "HMMR", "UQCRH", "AURKA", "CDC20", "TMEM123", "LAPTM4B", "PPP4R1", "YWHAQ", "STRA13", "SNRPD3", "AP3S1", "MYBL1", "RANBP1", "MDH1", "SMURF2", "UBE2E3", "PGAM1", "CKAP2", "NAP1L1", "ATP5F1", "ZWINT", "PSMC5", "NSA2", "FABP5", "QARS", "CDK2AP1", "PLBD1", "HIST1H4C", "PTMA", "HNRNPA1L2", "CDKN3"], "H3K9ac_keratinocyte_hg19": ["POP5", "AHCY", "TOMM40", "HDAC1", "CETN3", "TTK", "UQCR11", "PARK7", "RAD51AP1", "TMEM123", "SNRPD3", "RRM2", "CKAP2", "ATP5F1", "PSMC5", "SPCS1", "TRMT5", "PLBD1", "SNRNP25", "TRIP13", "HIST1H4C", "GAPDH", "HNRNPA1L2", "MAD2L1", "SLC25A6"], "H3K4me3_small intestine_mm9": ["IFITM3", "TOP2A", "POP5", "SERPINE1", "GMNN", "CETN3", "HSP90B1", "RAD51AP1", "CCNB2", "BLOC1S5", "XPO1", "YWHAQ", "NUSAP1", "POLR2I", "TMEM14A", "CBX5", "CAV2", "MYOF", "GNG11", "DHFR", "FOSL1", "PSMC5", "ADI1", "MCM3", "F2RL1", "MCM6"]}