{"H3K4me3_mammary epithelial cell_hg19": ["PTGFR", "CYFIP1", "PSMD14", "CETN3", "MYCBP2", "RPF2", "DCAF6", "HERPUD1", "CHSY1", "NCAM2", "PRKACB", "POLR2J", "PLEKHH1", "DUT", "RPS9", "MRPS27", "LIMCH1", "LRBA", "RPS5", "NSMCE1", "UBE2E2", "TBCB", "GULP1", "MLF2", "TBCK", "AR", "TMEFF2", "WDR82", "EEF1D", "EIF3L", "DMXL1", "RPL27A", "PPT1", "NDUFAF2", "TXNIP", "GARS", "MANSC1", "PTMA", "STEAP2", "ALDH9A1", "KLHDC9"], "H3K79me2_osteoblast_hg19": ["CUEDC2", "CETN3", "FAM35A", "DDX21", "ACACA", "IRF2BPL", "TRMT112", "MIEN1", "PPCS", "NKX3-1", "SNHG1", "PHYH", "DUT", "NDUFA3", "SNHG8", "NDUFA1", "TBCB", "GNB2L1", "NBPF15", "PSAT1", "RPL37A", "ARMCX6", "LAMTOR2", "PIGH", "RPS23"], "H3K4me3_HepG2_hg19": ["RPL4", "SETD7", "CETN3", "MYCBP2", "PRUNE2", "TXNDC12", "ARHGAP6", "DCAF6", "HERPUD1", "RPL7A", "CHSY1", "PDCD10", "FAM162A", "DSEL", "NARS2", "MXI1", "CDIPT", "TMEM14A", "PRKACB", "POLR2J", "SEC11A", "PLEKHH1", "BCAS2", "DUT", "LIMCH1", "LRBA", "BROX", "CMC1", "SNHG8", "UBE2E2", "MLF2", "EIF3L", "RPL27A", "NDUFAF2", "GARS", "MANSC1", "PRKD1", "AIDA", "PTMA", "STEAP2", "KLHDC9", "LRP11"], "H3K4me3_H1-hESC_hg19": ["CETN3", "PRUNE2", "RPF2", "PWP1", "ACACA", "HSP90B1", "TUBA1C", "PTDSS1", "RASSF3", "PDCD10", "PPCS", "MYO6", "NRIP1", "POLR2J", "TIMMDC1", "LIMCH1", "BROX", "CMC1", "COMMD3", "RPSA", "PJA2", "MANF", "NSA2", "EIF3L", "RPL7L1", "TTC3", "AIDA"], "H3K4me3_bone marrow macrophage_mm9": ["NCKAP1", "ARG2", "RPN2", "UBE2E3", "CETN3", "NDUFA1", "TXNDC12", "RABGGTB", "IPO7", "GNB2L1", "COPZ1", "HSP90B1", "LDHB", "NT5DC1", "PPCS", "ADI1", "DSEL", "DDIT4", "WAC", "TMEM14A", "SEC11A", "PLEKHH1", "NOP10", "PIGH"], "H3K9ac_mammary epithelial cell_hg19": ["CETN3", "NUCKS1", "RPF2", "PWP1", "DCAF6", "TUBA1C", "RASSF3", "PDCD10", "PRKACB", "PLEKHH1", "ARG2", "MRPS27", "TIMMDC1", "RPS5", "CMC1", "NDUFA1", "HDHD2", "PTRHD1", "MANF", "NSA2", "DMXL1", "TTC3", "VDAC2", "TAF7", "PSMG2", "RPS23"], "H3K4me3_HeLa-S3_hg19": ["SET", "CETN3", "MYCBP2", "ADK", "RPF2", "ACACA", "DCAF6", "HERPUD1", "PPP3CA", "CHSY1", "PDCD10", "RB1CC1", "MXI1", "PRKACB", "POLR2J", "SEC11A", "PLEKHH1", "HMGN1", "MRPS27", "LRBA", "RPS5", "BROX", "NSMCE1", "COMMD3", "UBE2E2", "TBCB", "RPSA", "GULP1", "MLF2", "TBCK", "DMXL1", "RPL27A", "WAC", "GARS", "MANSC1", "AIDA", "SERINC5", "KLHDC9", "ATF4"], "H3K4me3_brain_mm9": ["PTGFR", "RPN2", "CCNH", "CETN3", "PRUNE2", "EPRS", "IPO7", "HERPUD1", "PURA", "ATIC", "PPCS", "RDH11", "PBK", "ACADM", "TMEM14A", "SEC11A", "NKX3-1", "ARG2", "FBXL17", "TBCB", "GGCT", "TJP1", "ADI1", "DDIT4", "WAC", "BDP1", "MMADHC"], "H3K4me3_NT2-D1_hg19": ["MRPS27", "PEG3", "LIMCH1", "LRBA", "RPS5", "CETN3", "PRUNE2", "ADK", "NSMCE1", "COMMD3", "SQRDL", "ZCRB1", "PWP1", "RASSF3", "PDCD10", "PPCS", "FAM174A", "NARS2", "TTC3", "MANSC1", "AIDA", "BCAS2", "EIF4B", "ATF4"], "H3K4me3_thymus_mm9": ["NCKAP1", "SLC25A3", "CUEDC2", "CETN3", "FAM35A", "BMI1", "IPO7", "FAM216A", "SNX3", "BLOC1S5", "PPCS", "MYO6", "PBK", "TMEM14A", "SEC11A", "TBCB", "COPZ1", "TJP1", "TMEFF2", "ADI1", "WAC", "PSMG2", "STEAP1", "MMADHC", "AARS"], "H3K4me3_erythroblast_mm9": ["FTO", "RPL4", "PLGRKT", "PIGP", "SQRDL", "DCAF6", "HSP90B1", "PURA", "PPCS", "MYO6", "HLTF", "NCAM2", "HMGN1", "ARG2", "MRPS27", "TIMMDC1", "COMMD3", "UBE2E2", "HDHD2", "GNB2L1", "CCNB1IP1", "PJA2", "MLF2", "GGCT", "TMEFF2", "NSA2", "CMSS1", "MAP1B", "DDIT4", "PPT1", "NDUFAF2", "EBPL", "MANSC1", "STEAP1", "PIGH"], "H3K79me2_HepG2_hg19": ["RPL4", "CUEDC2", "ACACA", "IRF2BPL", "TRMT112", "MIEN1", "EPCAM", "FAM174A", "PRKACB", "SIL1", "BCAS2", "DUT", "TIMMDC1", "NDUFA3", "RPS5", "USP9Y", "SNHG8", "NSMCE1", "NDUFA1", "COPZ1", "COX6B1", "NBPF15", "NSA2", "ARMCX6", "LAMTOR2", "ALDH9A1", "RPS23"], "H3K9me3_ES-E14_mm9": ["DUT", "CETN3", "ACTR10"], "H3K27ac_keratinocyte_hg19": ["PIGP", "RPF2", "PWP1", "ACACA", "DCAF6", "CHSY1", "PPCS", "MKNK2", "RPL35", "PHYH", "ARG2", "UBE2E3", "NDUFA3", "BROX", "NSMCE1", "NDUFA1", "HDHD2", "GNB2L1", "EIF3L", "RPL7L1", "TTC3", "TAF7", "PSMG2", "AIDA", "STEAP2", "AARS"], "H3K4me3_A549_hg19": ["PTGFR", "DDC", "RPN2", "ARHGEF26", "GBE1", "CETN3", "PRUNE2", "MRPL36", "SQRDL", "RPF2", "PTPRF", "NME1-NME2", "PTDSS1", "CHSY1", "PDCD10", "PPCS", "EPCAM", "RB1CC1", "DSEL", "MYO6", "MXI1", "RPL35", "PRKACB", "POLR2J", "PLEKHH1", "ARG2", "MRPS27", "RPS5", "NSMCE1", "UBE2E2", "PTRHD1", "GULP1", "MLF2", "MANF", "ADI1", "EEF1D", "EIF3L", "DMXL1", "TXNIP", "GARS", "LRRN1", "MANSC1", "STEAP1", "PTMA", "SERINC5", "KLHDC9", "RPS23", "ATF4"], "H3K79me2_endothelial cell of umbilical vein_hg19": ["RPL4", "CUEDC2", "CETN3", "FAM35A", "ACACA", "IRF2BPL", "PURA", "TRMT112", "MIEN1", "PPCS", "CPNE3", "LTA4H", "ARG2", "CMTM4", "NDUFA3", "NSMCE1", "NDUFA1", "TBCB", "GNB2L1", "COX6B1", "NBPF15", "NGFRAP1", "ADI1", "ARMCX6", "LAMTOR2", "STEAP2", "PIGH"], "H3K27me3_brain_mm9": ["DSP", "PTGFR", "UBE2E3", "LRBA", "SLC30A4", "RASEF", "PRUNE2", "UBE2E2", "SQRDL", "BMI1", "SH3RF1", "TJP1", "TUBA1C", "MYO6", "MANSC1", "KCNN2", "CYSTM1", "NCAM2", "RLN1", "STEAP1", "RSL24D1", "PLEKHH1", "SERINC5"], "H3K4me3_placenta_mm9": ["NCKAP1", "CUEDC2", "SET", "CCNH", "PRUNE2", "UBE2E2", "IPO7", "COPZ1", "HSP90B1", "FAM216A", "TJP1", "TUBA1C", "TMEFF2", "GANAB", "MIEN1", "ADI1", "FAM162A", "DMXL1", "PBK", "STEAP1", "TMEM14A", "MMADHC", "NKX3-1"], "H3K4me3_brown adipose tissue_mm9": ["PTGFR", "C2CD5", "RPN2", "CETN3", "IPO7", "HSP90B1", "PURA", "BLOC1S5", "PTDSS1", "GANAB", "MIEN1", "CHSY1", "RDH11", "DSEL", "PBK", "TMEM14A", "PLEKHH1", "ARG2", "TJP1", "ADI1", "EIF3L", "DDIT4", "WAC", "MMADHC", "SERINC5", "ALDH9A1", "AARS"], "H3K4me3_small intestine_mm9": ["BCHE", "PTGFR", "DDC", "CUEDC2", "CETN3", "TBCB", "IPO7", "GNB2L1", "COPZ1", "HSP90B1", "TJP1", "BLOC1S5", "CHSY1", "PPCS", "ADI1", "RDH11", "DMXL1", "DSEL", "DDIT4", "PBK", "WAC", "TMEM14A", "MMADHC", "SERINC5"]}