{"H3K9ac_NT2-D1_hg19": ["SERPINE2", "SYT1", "ANXA4", "LY75", "CXCL1", "PRDM1", "NME5", "DHRS1", "PDZK1IP1", "CLDN1", "OGFRL1", "IL6", "PLAU", "SCNN1A", "NFKBIZ", "SLC17A5", "MDM2", "EPSTI1", "SERPING1", "TCP11L2", "KCTD11", "CHSY3"], "H2AFZ_HeLa-S3_hg19": ["PMEL", "IFITM1", "ST6GALNAC2", "CFH", "MX2", "DAPP1", "LYPD3", "DHRS1", "DDX60", "FBXO32", "ZFYVE1", "POLB", "OGFRL1", "EPB41L4A", "TMEM159", "RRM2B", "LIPH", "SLC17A5", "RAET1L", "LPXN", "SERINC1", "CD58"], "H3K9ac_H1-hESC_hg19": ["SLFN5", "DUSP5", "PMEL", "IFITM1", "STEAP4", "ANXA4", "LY75", "TM6SF1", "NDRG1", "ABTB1", "PRDX5", "SLC6A9", "CCNG2", "MYO5B", "PNOC", "NFKBIZ", "TP53INP1", "EPSTI1", "AOX1", "SERPING1", "SCN5A", "ANKRA2"], "H3K27ac_B cell_hg19": ["GRAMD1C", "STARD4", "RSAD2", "ANXA4", "HSD17B14", "PRDM1", "IL1RAP", "FBXO32", "IFIT1", "USP18", "DUSP6", "POLB", "PRDX5", "TUBA1A", "IL1B", "DDIT3", "SLC17A5", "KCTD11", "TLR4", "LOC339803", "RBMS2", "TMEM45A"], "H3K36me3_mammary epithelial cell_hg19": ["BNIP3L", "PMEL", "SERPINB1", "CSF2", "CCL20", "AMIGO2", "MYH16", "C10ORF10", "MIR487A", "ADM", "INHBA", "PRDX5", "SCNN1A", "DDIT4", "MDM2", "SLITRK6", "LPXN", "FSD2", "S100A14", "SPATA18", "SLC16A4", "SCN1B"], "H3K4me3_ES-E14_mm9": ["SLFN5", "TMEM87B", "STEAP4", "ST6GALNAC2", "DGKA", "CXCL1", "IL1RAP", "GRAMD3", "AREG", "USP18", "PLA2G7", "LOXL2", "IFIT2", "CACNG6", "STC2", "HIVEP2", "PGPEP1", "WARS", "LAPTM5", "CYBRD1", "WIPI1", "CFLAR", "PNMA2", "FBXO32", "GFRA2", "TMEM154", "MARCH3", "ACER2", "ANO1", "TTC9", "P2RX4", "SCNN1A", "SLCO2A1", "KCNMA1", "SPATA18", "XAF1", "TMEM45A", "DSC3"], "H4K20me1_fibroblast of lung_hg19": ["PTPRR", "STEAP4", "RBMY2EP", "PPM1N", "LAPTM5", "CYBRD1", "SLC2A3", "GLRX", "TM6SF1", "PARP9", "ADAMTS5", "TUBA1A", "SLPI", "MIR154", "DDIT3", "DDIT4", "MDM2", "UQCRBP1", "XCL1", "FSD2", "VIM", "SCN5A", "SLC16A4", "SCN1B"], "H3K27ac_heart_mm9": ["TMEM87B", "ACSS2", "STEAP4", "ST6GALNAC2", "DGKA", "DAPP1", "NEDD9", "CXCL1", "DDX60", "ZFYVE1", "NDRG1", "IFI44L", "IFIT2", "ADAMTS5", "TUBA1A", "PLAU", "TCP11L2", "BNIP3L", "DUSP5", "GABARAPL1", "STARD4", "RSAD2", "IFI44", "SEPP1", "PLA2G16", "LMBRD1", "TMEM159", "OAS2", "CTH", "COL6A3", "VIM", "TLR4"], "H3K79me2_keratinocyte_hg19": ["ARSA", "ZNF671", "GABARAPL1", "TM4SF19", "LXN", "WARS", "CXCL1", "LYPD3", "DHRS1", "DDX60", "SNORD116-1", "AREG", "HMGCL", "PRDX5", "PLAU", "DDIT3", "DDIT4", "NFKBIZ", "KCTD11", "XAF1", "MGLL", "TMEM45A"], "H3K4me3_cardiac mesoderm_hg19": ["ST6GALNAC2", "TGFA", "CXCL1", "PLOD2", "PRDM1", "USP18", "TOB1", "ADAMTS5", "EPB41L4A", "TUBA1A", "STC2", "EPSTI1", "TCP11L2", "CHSY3", "PGPEP1", "SCN1B", "ANXA4", "NOG", "MX1", "CFLAR", "NME5", "DHRS1", "PARP9", "GFRA2", "PM20D1", "ABTB1", "TTC9", "LMBRD1", "IL6", "SLC6A9", "MYO5B", "GPR160", "RAET1L", "SERINC1", "KCTD11", "VIM", "ANKRA2", "ALDH7A1", "YPEL2", "MATN2", "DSC3"], "H3K4me3_HEK293_hg19": ["SLFN5", "TM4SF19", "STARD4", "SERPINB1", "IFITM2", "ST6GALNAC2", "EPAS1", "CXCL1", "PRDM1", "WFDC2", "TTC9", "IL6", "RRM2B", "PCDHB18", "STC2", "MYO5B", "TP53INP1", "EPSTI1", "ANKRD1", "KCTD11", "CHSY3", "SCN1B", "TMEM45A"], "H4K20me1_H1-hESC_hg19": ["SLFN5", "ARSA", "GABARAPL1", "TMPRSS3", "SLC2A3", "ADM", "VLDLR", "IL1RAP", "DHRS1", "FBXO32", "TMC4", "CSF2RA", "DUSP6", "TM7SF2", "ACER2", "ELF3", "SPOCK2", "DDIT3", "UQCRBP1", "NCAM1", "ULBP1", "SCN1B", "IDO1"], "H3ac_C2C12_mm9": ["WARS", "SERPINE2", "ARRDC3", "LY75", "TGFA", "CXCL1", "PLOD2", "PRDM1", "FBXO32", "PLA2G7", "LOXL2", "MARCH3", "POLB", "OGFRL1", "P2RX4", "RRM2B", "REEP3", "RHOJ", "TXNIP", "TCP11L2", "PGPEP1", "ANKRA2", "SCN1B"], "H3K4me3_CD14-positive monocyte_hg19": ["ACSS3", "ACSS2", "CFH", "CXCL1", "PLOD2", "VLDLR", "USP18", "CLDN1", "ADAMTS5", "EPB41L4A", "SLC17A5", "EPSTI1", "AOX1", "LPXN", "ENPP4", "CHSY3", "GPC4", "PGPEP1", "ENPP5", "LOC339803", "ARSA", "SLC2A14", "RSAD2", "NOG", "IL18", "ZNF300P1", "NME5", "C15ORF54", "PM20D1", "ABTB1", "IL6", "TRAPPC6A", "PSAT1", "CTH", "ZNF737", "RBMS2", "RPL23AP53", "YPEL2", "TMEM45A", "DSC3"], "H3K4me3_myocyte_mm9": ["TMEM87B", "BTG1", "DDX58", "ANXA4", "DGKA", "NOG", "LY75", "CXCL1", "DDX60", "GRAMD3", "SEPP1", "PLA2G7", "PNRC1", "POLB", "APH1B", "SPOCK2", "NFKBIZ", "TCP11L2", "TK2", "HIVEP2", "ANKRA2", "YPEL5", "ALDH7A1"], "H3K4me3_placenta_mm9": ["DUSP5", "STARD4", "STEAP4", "DGKA", "LY75", "CYBRD1", "WIPI1", "AREG", "USP18", "ACER2", "ANO1", "PRDX5", "P2RX4", "APH1B", "PLAU", "MYO5B", "MALL", "ENPP4", "SCN5A", "SPATA18", "SCN1B"], "H3K4me3_HepG2_hg19": ["SLFN5", "TMEM87B", "ACSS2", "EPAS1", "PPM1N", "PRDM1", "DDX60", "TOB1", "IFIT2", "PLAU", "KYNU", "LIPH", "NFKBIZ", "TP53INP1", "SLC17A5", "EPSTI1", "TCP11L2", "CHSY3", "S100A14", "SCN5A", "GPC4", "TSPAN1", "SCN1B", "ARSA", "SERPINB1", "WARS", "TSC22D1", "MX2", "GFRA2", "IL6", "P2RX4", "SLC6A9", "RRM2B", "RASA4", "OAS2", "KCTD11", "XAF1", "ANKRA2", "INA", "RBMS2", "DSC3"], "H3K4me3_brown adipose tissue_mm9": ["PTPRR", "STARD4", "STEAP4", "ITGB4", "LY75", "IFI44", "ASNS", "CXCL1", "MR1", "AREG", "ZFYVE1", "SEPP1", "CLDN1", "TTC9", "ADAMTS5", "TMEM159", "STC2", "MYO5B", "DDIT4", "LPXN", "TLR4", "ENPP5", "SCN1B"], "H3K4me3_CH12.LX_mm9": ["TMEM87B", "ACSS2", "SERPINE2", "NEDD9", "DDX60", "IFIT1", "USP18", "TOB1", "ZFYVE1", "NDRG1", "IFIT2", "POLB", "PRDX5", "APH1B", "CYSLTR2", "PLAU", "LIPH", "SLC17A5", "TCP11L2", "ENPP4", "HIVEP2", "PGPEP1", "SCN1B", "STARD4", "WARS", "TNFSF15", "MX2", "WIPI1", "CFLAR", "KLHL24", "NME5", "FBXO32", "DUSP6", "MARCH3", "ACER2", "ABTB1", "TRAPPC6A", "P2RX4", "RRM2B", "RASA4", "CCNG2", "MALL", "GPR160", "KCTD11", "VIM", "XAF1", "ANKRA2", "ALDH7A1"], "H3K4me3_small intestine_mm9": ["DUSP5", "ACSS3", "STEAP4", "NNMT", "TNFSF15", "LY75", "IL18", "IFI44", "ASNS", "CXCL1", "PLAT", "NME5", "AREG", "CLDN1", "PLA2G7", "ADAMTS5", "TRAPPC6A", "TMEM159", "MALL", "DDIT4", "SLITRK6", "LPXN", "TLR4"]}