{"H4K20me1_mammary epithelial cell_hg19": ["CDKN1C", "CAMK2D", "JUN", "EXOC8", "TMEM176A", "NR1D2", "FOS", "KLHDC7B", "KLF4", "PARP9", "MOV10", "HSH2D", "MT2A", "SCML1", "NUDCD1", "SCO2", "SPATS2L", "HEATR3", "CLC", "ZACN", "HIST1H2AC", "APOBEC3A", "UBQLN2", "DACT1"], "H2AFZ_skeletal muscle myoblast_hg19": ["TMEM55A", "CD164", "DTX3L", "CHUK", "SAMD9", "FLT3", "ZDHHC20", "C1GALT1", "NEXN", "GDPD2", "ADAR", "DDX60L", "AHR", "USP18", "FHIT", "DUSP6", "PRRG4", "MOB1A", "OAS2", "OAS3", "HPSE", "LGALS9", "GPR155", "UBQLN2"], "H3K36me3_CH12.LX_mm9": ["SCARB2", "IFITM2", "GPR21", "TXK", "NEXN", "ADAR", "IFI35", "IPO4", "TMA16", "SLC5A5", "TYMP", "SLC22A15", "NUDCD1", "HEATR3", "FBXO6", "ACADM", "HSF5", "SCYL2", "DACT1", "JUND", "SLC31A2", "EXOC8", "CHUK", "ACSL1", "C1GALT1", "TMEM176A", "TTC7B", "SLC6A12", "EIF2AK2", "KLF4", "PARP9", "MLH3", "FKBP1A", "MOV10", "CXCL10", "HSH2D", "PLSCR1", "SCO2", "IRF2", "IRF7", "PLEKHM1", "PSME2", "CD69", "HSPA1B", "ALDH9A1", "HSPA1A"], "H3K79me2_fibroblast of dermis_hg19": ["IFITM3", "LGALS3BP", "SAMD9L", "IFITM1", "SERPINB2", "PNPT1", "CISH", "DTX3L", "WBP2", "DDX60L", "IFI35", "MTMR4", "PARP9", "PLSCR1", "MT2A", "SCO2", "PSTPIP2", "TRIM5", "ID1", "CENPK", "CCL2", "SLC38A6", "XAF1", "CHMP5"], "H3K27me3_brain_mm9": ["FLT3", "LRRK2", "LY75", "LGALSL", "TMEM123", "FAM134B", "EPHB2", "JAK2", "PAMR1", "SYT2", "ITGA4", "DTX3L", "CHUK", "DDX58", "IL15", "HEG1", "TTC7B", "PARP12", "ID1", "IRF7", "SPATS2L", "TRIM58", "HPSE", "FKBP9", "RGL1"], "H3K4me3_erythroblast_mm9": ["TBC1D19", "SAMD9L", "SGMS1", "LRRK2", "LGALSL", "TMEM140", "DDX60", "RNF157", "FAM134B", "SLC22A15", "SNAPC3", "TNFSF10", "SLC38A6", "GBP2", "EPHB2", "SCYL2", "SYT2", "WARS", "EXOC8", "DTX3L", "MID1IP1", "STAT2", "ISG15", "MLH3", "PER2", "UGDH", "CXCL10", "IRF2", "CENPK", "SPATS2L", "HPSE", "XAF1", "STX1A"], "H3K79me2_keratinocyte_hg19": ["IFITM3", "CYP2J2", "WARS", "DTX3L", "MMD", "ISG15", "DDX60L", "IFI35", "TOR1B", "DDX60", "HIST2H2BE", "MT2A", "APOL6", "IFI27", "SCO2", "TRIM5", "ID1", "TNFSF10", "FOSB", "HIST1H3H", "XAF1", "TRIM22", "TMEM45A"], "H3K27ac_HCT116_hg19": ["SCARB2", "TMEM55A", "IFITM3", "RB1", "CD164", "TBC1D19", "STARD4", "DTX3L", "SP110", "SNX10", "USP18", "HIST2H2BE", "PRRG4", "UGDH", "SLC22A15", "HSPH1", "SNAPC3", "OAS3", "SLC38A6", "CMPK2", "SLC25A43", "UBQLN2", "ZNF354B"], "H3K27ac_limb_mm9": ["SCARB2", "KLF10", "ZDHHC20", "LRRK2", "SCLT1", "NEXN", "ADAR", "IFI35", "TOR1B", "MTMR4", "MLH3", "IFI44L", "ENKUR", "MOB1A", "NUDCD1", "SDPR", "AXL", "CENPK", "UBA2", "HEATR3", "ACADM", "DLEU2", "TMED7", "GLUL"], "H3K79me2_C2C12_mm9": ["TMEM55A", "IFITM3", "KLF10", "RAB2B", "TCF7L2", "PNPT1", "WARS", "EXOC8", "JUP", "ARRDC3", "MYOF", "UBE2D1", "ADAR", "CRNKL1", "TMA16", "MARCKS", "CTSL", "PLEKHM1", "CCL2", "SLC38A6", "SRFBP1", "SCYL2", "CHMP5"], "H3K9me3_ES-E14_mm9": ["SP110", "GBP3"], "H3K9me3_mononuclear cell_hg19": ["CYP2J2", "C2ORF16", "LRIF1"], "H3K27me3_GM12878_hg19": ["CDKN1C", "FLT3", "AMIGO2", "SGMS2", "SLC5A5", "EPS8", "RNF157", "FAM134B", "NHSL2", "SCML1", "PRKAR2B", "CA2", "CD38", "EPHB2", "GLUL", "PAMR1", "SYT2", "PLK2", "TMEM176A", "MYOF", "NR1D2", "FOS", "ELOVL7", "HBA1", "KLF4", "DUSP6", "ETV7", "TMEM2", "FMNL2", "SDPR", "ID1", "FOSB", "TRIM58", "HPSE", "FKBP9", "ZACN", "LINC00487", "STX1A"], "H3ac_C2C12_mm9": ["RB1", "PGAP1", "WARS", "DTX3L", "SGMS1", "STAT2", "ARRDC3", "LY75", "UBE2L6", "IFI35", "ASAP2", "MLH3", "TMA16", "TMEM169", "PPIP5K2", "CENPK", "PLEKHM1", "UBA2", "DLEU2", "LRIF1", "RGL1", "GBP2", "JAK2"], "H3K4me3_G1E-ER4_mm9": ["RGS18", "TBC1D19", "WBP2", "PPM1K", "TMEM140", "RNF157", "CTSL", "TNFSF10", "SLC38A6", "DLEU2", "TMED7", "SCYL2", "KLF10", "JUN", "PNPT1", "SLC31A2", "GCH1", "STAT1", "ACSL1", "MMD", "TMEM176A", "SCLT1", "EIF2AK2", "FKBP1A", "UGDH", "CXCL10", "MARCKS", "TCN2", "CENPK", "SPATS2L", "PSME2", "STX1A"], "H3K79me2_liver_mm9": ["CD164", "IFITM2", "EXOC8", "CHUK", "DDX58", "TMEM176A", "CUL1", "SGMS2", "IFI35", "AHR", "MOB1A", "CXCL11", "XK", "TMX1", "CTSL", "SNAPC3", "PLEKHM1", "UBA2", "SRFBP1", "DLEU2", "TMED7", "CHMP5"], "H4K20me1_fibroblast of lung_hg19": ["CAMK2D", "C5AR1", "ADAR", "PPM1K", "ASAP2", "AHR", "EPS8", "SCML1", "NUDCD1", "FSD2", "SLC25A43", "TMED7", "HIST1H2AC", "UBQLN2", "JUND", "EXOC8", "PLK2", "NR1D2", "FOS", "PARP9", "UGDH", "MOB1A", "HSH2D", "SPATS2L", "UBA2"], "H3K79me2_A549_hg19": ["LGALS3BP", "SLFN5", "TBC1D19", "WBP2", "IFI35", "DDX60", "USP18", "CACNG6", "MT2A", "TMEM169", "SCML1", "TRIM5", "CCL2", "HIST1H3H", "MEST", "NIPSNAP3A", "DTX3L", "CHUK", "ACSL1", "STAT2", "FOS", "ELOVL7", "TOR1B", "KLF4", "PARP9", "HIST2H2BE", "MOV10", "OAS1", "CENPK", "NUCB1", "PSME2", "FKBP9", "FKBP5"], "H2AFZ_mammary epithelial cell_hg19": ["SCARB2", "CYP2J2", "RAB2B", "IFITM1", "IFITM2", "CISH", "STAT1", "FLT3", "WBP2", "C1GALT1", "MYOF", "ISG15", "ASAP2", "USP18", "NHSL2", "XK", "OAS2", "TMX1", "OAS3", "SLC38A6", "DLEU2", "RGL1", "TMED7"], "H3K4me2_mammary epithelial cell_hg19": ["IFITM2", "FLT3", "HBD", "TMEM140", "IFIT1", "USP18", "OASL", "NHSL2", "PRKAR2B", "DLEU2", "DACT1", "CYP2J2", "RAB2B", "SYT2", "RSAD2", "DTX3L", "ISG15", "UGDH", "CXCL11", "XK", "CENPK", "CMPK2", "LY6E", "TMEM45A", "ZNF354B"]}